smretrofit/__init__.py
smretrofit/smretrofit.py
smretrofit-1.0.4.dist-info/METADATA
smretrofit-1.0.4.dist-info/WHEEL
smretrofit-1.0.4.dist-info/top_level.txt
smretrofit-1.0.4.dist-info/RECORD
