Metadata-Version: 2.1
Name: smretrofit
Version: 1.0.4
Home-page: https://www.somikoron.ai
Author: Somikoron
Author-email: contact@somikoron.ai
License: Somikoron License
Project-URL: Documentation, https://api.somikoron.ai
Project-URL: Source, https://github.com/somikoronAI-Source/smretrofit.git
Project-URL: Bug Tracker, https://github.com/somikoronAI-Source/smretrofit/issues/1
Keywords: computer vision requests image and video processing
Classifier: Development Status :: 5 - Production/Stable
Classifier: Intended Audience :: Developers
Classifier: License :: Other/Proprietary License
Classifier: Operating System :: OS Independent
Requires-Python: >=3.7
Requires-Dist: opencv-python
Requires-Dist: requests
Requires-Dist: Pillow
Requires-Dist: numpy
